{"title":"Final GDP Price Index q/q","slug":"final-gdp-price-index-q-q","cur":"USD","ebaseId":46,"updated":"2026-06-21T01:36:47.020Z","history":[{"date":"Jun 25, 2026","actual":"","forecast":"3.5%","previous":"3.5%","actColor":"","impact":"medium"},{"date":"Apr 9, 2026","actual":"3.7%","forecast":"3.8%","previous":"3.8%","actColor":"","impact":"medium"},{"date":"Jan 22, 2026","actual":"3.8%","forecast":"3.8%","previous":"3.8%","actColor":"","impact":"medium"},{"date":"Sep 25, 2025","actual":"2.1%","forecast":"2.0%","previous":"2.0%","actColor":"","impact":"medium"},{"date":"Jun 26, 2025","actual":"3.8%","forecast":"3.7%","previous":"3.7%","actColor":"","impact":"medium"},{"date":"Mar 27, 2025","actual":"2.3%","forecast":"2.4%","previous":"2.4%","actColor":"","impact":"medium"},{"date":"Dec 19, 2024","actual":"1.9%","forecast":"1.9%","previous":"1.9%","actColor":"","impact":"medium"},{"date":"Sep 26, 2024","actual":"2.5%","forecast":"2.5%","previous":"2.5%","actColor":"","impact":"medium"},{"date":"Jun 27, 2024","actual":"3.1%","forecast":"3.0%","previous":"3.0%","actColor":"","impact":"medium"},{"date":"Mar 28, 2024","actual":"1.6%","forecast":"1.6%","previous":"1.6%","actColor":"","impact":"medium"},{"date":"Dec 21, 2023","actual":"3.3%","forecast":"3.6%","previous":"3.6%","actColor":"bad","impact":"medium"},{"date":"Sep 28, 2023","actual":"1.7%","forecast":"2.0%","previous":"2.0%","actColor":"bad","impact":"medium"},{"date":"Jun 29, 2023","actual":"4.1%","forecast":"4.2%","previous":"4.2%","actColor":"","impact":"medium"},{"date":"Mar 30, 2023","actual":"3.9%","forecast":"3.9%","previous":"3.9%","actColor":"","impact":"medium"},{"date":"Dec 22, 2022","actual":"4.4%","forecast":"4.3%","previous":"4.3%","actColor":"","impact":"low"},{"date":"Sep 29, 2022","actual":"9.0%","forecast":"8.9%","previous":"8.9%","actColor":"","impact":"low"},{"date":"Jun 29, 2022","actual":"8.2%","forecast":"8.1%","previous":"8.1%","actColor":"","impact":"low"},{"date":"Mar 30, 2022","actual":"7.1%","forecast":"7.1%","previous":"7.1%","actColor":"","impact":"low"},{"date":"Dec 22, 2021","actual":"6.0%","forecast":"5.9%","previous":"5.9%","actColor":"","impact":"low"},{"date":"Sep 30, 2021","actual":"6.1%","forecast":"6.1%","previous":"6.1%","actColor":"","impact":"low"},{"date":"Jun 24, 2021","actual":"4.3%","forecast":"4.3%","previous":"4.3%","actColor":"","impact":"low"},{"date":"Mar 25, 2021","actual":"2.0%","forecast":"2.1%","previous":"2.1%","actColor":"","impact":"low"},{"date":"Dec 22, 2020","actual":"3.5%","forecast":"3.6%","previous":"3.6%","actColor":"","impact":"low"},{"date":"Sep 30, 2020","actual":"-1.8%","forecast":"-2.0%","previous":"-2.0%","actColor":"good","impact":"low"}]}