{"title":"Household Spending y/y","slug":"household-spending-y-y","cur":"JPY","ebaseId":359,"updated":"2026-07-10T13:39:04.510Z","history":[{"date":"Jul 7, 2026","actual":"-0.4%","forecast":"-2.3%","previous":"-0.5%","actColor":"good","impact":"low"},{"date":"Jun 5, 2026","actual":"-0.5%","forecast":"-1.5%","previous":"-2.9%","actColor":"good","impact":"low"},{"date":"May 12, 2026","actual":"-2.9%","forecast":"-1.4%","previous":"-1.8%","actColor":"bad","impact":"low"},{"date":"Apr 7, 2026","actual":"-1.8%","forecast":"-0.8%","previous":"-1.0%","actColor":"bad","impact":"low"},{"date":"Mar 10, 2026","actual":"-1.0%","forecast":"2.4%","previous":"-2.6%","actColor":"bad","impact":"low"},{"date":"Feb 6, 2026","actual":"-2.6%","forecast":"-0.5%","previous":"2.9%","actColor":"bad","impact":"low"},{"date":"Jan 9, 2026","actual":"2.9%","forecast":"-1.0%","previous":"-3.0%","actColor":"good","impact":"low"},{"date":"Dec 5, 2025","actual":"-3.0%","forecast":"1.1%","previous":"1.8%","actColor":"bad","impact":"low"},{"date":"Nov 7, 2025","actual":"1.8%","forecast":"2.5%","previous":"2.3%","actColor":"bad","impact":"low"},{"date":"Oct 7, 2025","actual":"2.3%","forecast":"1.4%","previous":"1.4%","actColor":"good","impact":"low"},{"date":"Sep 5, 2025","actual":"1.4%","forecast":"2.2%","previous":"1.3%","actColor":"bad","impact":"low"},{"date":"Aug 8, 2025","actual":"1.3%","forecast":"2.8%","previous":"4.7%","actColor":"bad","impact":"low"},{"date":"Jul 4, 2025","actual":"4.7%","forecast":"1.3%","previous":"-0.1%","actColor":"good","impact":"low"},{"date":"Jun 6, 2025","actual":"-0.1%","forecast":"1.5%","previous":"2.1%","actColor":"bad","impact":"low"},{"date":"May 9, 2025","actual":"2.1%","forecast":"0.2%","previous":"-0.5%","actColor":"good","impact":"low"},{"date":"Apr 4, 2025","actual":"-0.5%","forecast":"-0.9%","previous":"0.8%","actColor":"good","impact":"low"},{"date":"Mar 11, 2025","actual":"0.8%","forecast":"3.7%","previous":"2.7%","actColor":"bad","impact":"low"},{"date":"Feb 7, 2025","actual":"2.7%","forecast":"0.5%","previous":"-0.4%","actColor":"good","impact":"low"},{"date":"Jan 10, 2025","actual":"-0.4%","forecast":"-0.8%","previous":"-1.3%","actColor":"good","impact":"low"},{"date":"Dec 6, 2024","actual":"-1.3%","forecast":"-2.6%","previous":"-1.1%","actColor":"good","impact":"low"},{"date":"Nov 8, 2024","actual":"-1.1%","forecast":"-1.8%","previous":"-1.9%","actColor":"good","impact":"low"},{"date":"Oct 8, 2024","actual":"-1.9%","forecast":"-2.5%","previous":"0.1%","actColor":"good","impact":"low"},{"date":"Sep 6, 2024","actual":"0.1%","forecast":"1.2%","previous":"-1.4%","actColor":"bad","impact":"low"},{"date":"Aug 6, 2024","actual":"-1.4%","forecast":"-0.9%","previous":"-1.8%","actColor":"bad","impact":"low"}]}