{"title":"MI Leading Index m/m","slug":"mi-leading-index-m-m","cur":"AUD","ebaseId":303,"updated":"2026-06-24T13:31:55.100Z","history":[{"date":"Jun 17, 2026","actual":"0.0%","forecast":"","previous":"0.0%","actColor":"","impact":"low"},{"date":"May 27, 2026","actual":"0.0%","forecast":"","previous":"-0.1%","actColor":"","impact":"low"},{"date":"Apr 22, 2026","actual":"-0.1%","forecast":"","previous":"-0.1%","actColor":"","impact":"low"},{"date":"Mar 18, 2026","actual":"-0.1%","forecast":"","previous":"-0.1%","actColor":"","impact":"low"},{"date":"Feb 18, 2026","actual":"-0.1%","forecast":"","previous":"0.1%","actColor":"","impact":"low"},{"date":"Jan 21, 2026","actual":"0.1%","forecast":"","previous":"0.0%","actColor":"","impact":"low"},{"date":"Dec 17, 2025","actual":"0.0%","forecast":"","previous":"0.1%","actColor":"","impact":"low"},{"date":"Nov 19, 2025","actual":"0.1%","forecast":"","previous":"0.0%","actColor":"","impact":"low"},{"date":"Oct 15, 2025","actual":"0.0%","forecast":"","previous":"0.0%","actColor":"","impact":"low"},{"date":"Sep 17, 2025","actual":"0.0%","forecast":"","previous":"0.1%","actColor":"","impact":"low"},{"date":"Aug 27, 2025","actual":"0.1%","forecast":"","previous":"0.0%","actColor":"","impact":"low"},{"date":"Jul 23, 2025","actual":"0.0%","forecast":"","previous":"-0.1%","actColor":"","impact":"low"},{"date":"Jun 18, 2025","actual":"-0.1%","forecast":"","previous":"0.0%","actColor":"","impact":"low"},{"date":"May 21, 2025","actual":"0.0%","forecast":"","previous":"-0.1%","actColor":"","impact":"low"},{"date":"Apr 16, 2025","actual":"-0.1%","forecast":"","previous":"0.1%","actColor":"","impact":"low"},{"date":"Mar 19, 2025","actual":"0.1%","forecast":"","previous":"0.1%","actColor":"","impact":"low"},{"date":"Feb 19, 2025","actual":"0.1%","forecast":"","previous":"0.0%","actColor":"","impact":"low"},{"date":"Jan 22, 2025","actual":"0.0%","forecast":"","previous":"0.1%","actColor":"","impact":"low"},{"date":"Dec 18, 2024","actual":"0.1%","forecast":"","previous":"0.2%","actColor":"","impact":"low"},{"date":"Nov 20, 2024","actual":"0.2%","forecast":"","previous":"0.0%","actColor":"","impact":"low"},{"date":"Oct 16, 2024","actual":"0.0%","forecast":"","previous":"-0.1%","actColor":"","impact":"low"},{"date":"Sep 18, 2024","actual":"-0.1%","forecast":"","previous":"0.0%","actColor":"","impact":"low"},{"date":"Aug 21, 2024","actual":"0.0%","forecast":"","previous":"0.0%","actColor":"","impact":"low"},{"date":"Jul 17, 2024","actual":"0.0%","forecast":"","previous":"0.0%","actColor":"","impact":"low"}]}