{"title":"Net Lending to Individuals m/m","slug":"net-lending-to-individuals-m-m","cur":"GBP","ebaseId":343,"updated":"2026-06-24T13:19:43.078Z","history":[{"date":"Jun 2, 2026","actual":"6.2B","forecast":"7.1B","previous":"8.0B","actColor":"bad","impact":"low"},{"date":"May 1, 2026","actual":"8.0B","forecast":"5.9B","previous":"6.8B","actColor":"good","impact":"low"},{"date":"Mar 30, 2026","actual":"6.8B","forecast":"5.6B","previous":"5.9B","actColor":"good","impact":"low"},{"date":"Mar 2, 2026","actual":"5.9B","forecast":"6.2B","previous":"6.1B","actColor":"bad","impact":"low"},{"date":"Jan 30, 2026","actual":"6.1B","forecast":"6.1B","previous":"6.6B","actColor":"","impact":"low"},{"date":"Jan 5, 2026","actual":"6.6B","forecast":"5.2B","previous":"5.4B","actColor":"good","impact":"low"},{"date":"Dec 1, 2025","actual":"5.4B","forecast":"6.4B","previous":"7.0B","actColor":"bad","impact":"low"},{"date":"Oct 29, 2025","actual":"7.0B","forecast":"5.6B","previous":"6.0B","actColor":"good","impact":"low"},{"date":"Sep 29, 2025","actual":"6.0B","forecast":"6.3B","previous":"6.1B","actColor":"bad","impact":"low"},{"date":"Sep 1, 2025","actual":"6.1B","forecast":"4.9B","previous":"6.8B","actColor":"good","impact":"low"},{"date":"Jul 29, 2025","actual":"6.8B","forecast":"3.7B","previous":"2.9B","actColor":"good","impact":"low"},{"date":"Jun 30, 2025","actual":"2.9B","forecast":"4.1B","previous":"0.8B","actColor":"bad","impact":"low"},{"date":"Jun 2, 2025","actual":"0.8B","forecast":"2.8B","previous":"13.8B","actColor":"bad","impact":"low"},{"date":"May 1, 2025","actual":"13.8B","forecast":"4.4B","previous":"4.6B","actColor":"good","impact":"low"},{"date":"Mar 31, 2025","actual":"4.6B","forecast":"4.9B","previous":"5.9B","actColor":"bad","impact":"low"},{"date":"Mar 3, 2025","actual":"5.9B","forecast":"4.7B","previous":"4.6B","actColor":"good","impact":"low"},{"date":"Jan 30, 2025","actual":"4.6B","forecast":"3.6B","previous":"3.4B","actColor":"good","impact":"low"},{"date":"Jan 3, 2025","actual":"3.4B","forecast":"4.4B","previous":"4.5B","actColor":"bad","impact":"low"},{"date":"Nov 29, 2024","actual":"4.5B","forecast":"4.1B","previous":"3.8B","actColor":"good","impact":"low"},{"date":"Oct 29, 2024","actual":"3.8B","forecast":"4.1B","previous":"4.2B","actColor":"bad","impact":"low"},{"date":"Sep 30, 2024","actual":"4.2B","forecast":"4.1B","previous":"4.0B","actColor":"","impact":"low"},{"date":"Aug 30, 2024","actual":"4.0B","forecast":"3.4B","previous":"3.8B","actColor":"good","impact":"low"},{"date":"Jul 29, 2024","actual":"3.8B","forecast":"2.2B","previous":"2.7B","actColor":"good","impact":"low"},{"date":"Jul 1, 2024","actual":"2.7B","forecast":"3.3B","previous":"3.1B","actColor":"bad","impact":"low"}]}