{"title":"Pending Home Sales m/m","slug":"pending-home-sales-m-m","cur":"USD","ebaseId":233,"updated":"2026-07-10T13:49:40.508Z","history":[{"date":"Jun 17, 2026","actual":"3.8%","forecast":"0.8%","previous":"1.4%","actColor":"good","impact":"low"},{"date":"May 19, 2026","actual":"1.4%","forecast":"1.0%","previous":"1.5%","actColor":"good","impact":"medium"},{"date":"Apr 21, 2026","actual":"1.5%","forecast":"0.0%","previous":"1.8%","actColor":"good","impact":"medium"},{"date":"Mar 17, 2026","actual":"1.8%","forecast":"-0.6%","previous":"-0.8%","actColor":"good","impact":"medium"},{"date":"Feb 19, 2026","actual":"-0.8%","forecast":"1.4%","previous":"-9.3%","actColor":"bad","impact":"medium"},{"date":"Jan 21, 2026","actual":"-9.3%","forecast":"-0.3%","previous":"3.3%","actColor":"bad","impact":"medium"},{"date":"Dec 29, 2025","actual":"3.3%","forecast":"1.0%","previous":"1.9%","actColor":"good","impact":"medium"},{"date":"Nov 25, 2025","actual":"1.9%","forecast":"0.5%","previous":"0.0%","actColor":"good","impact":"medium"},{"date":"Oct 29, 2025","actual":"0.0%","forecast":"1.6%","previous":"4.0%","actColor":"bad","impact":"medium"},{"date":"Sep 29, 2025","actual":"4.0%","forecast":"0.2%","previous":"-0.4%","actColor":"good","impact":"medium"},{"date":"Aug 28, 2025","actual":"-0.4%","forecast":"-0.4%","previous":"-0.8%","actColor":"","impact":"medium"},{"date":"Jul 30, 2025","actual":"-0.8%","forecast":"0.2%","previous":"1.8%","actColor":"bad","impact":"medium"},{"date":"Jun 26, 2025","actual":"1.8%","forecast":"0.2%","previous":"-6.3%","actColor":"good","impact":"medium"},{"date":"May 29, 2025","actual":"-6.3%","forecast":"-0.9%","previous":"6.1%","actColor":"bad","impact":"medium"},{"date":"Apr 30, 2025","actual":"6.1%","forecast":"0.9%","previous":"2.0%","actColor":"good","impact":"medium"},{"date":"Mar 27, 2025","actual":"2.0%","forecast":"0.9%","previous":"-4.6%","actColor":"good","impact":"medium"},{"date":"Feb 27, 2025","actual":"-4.6%","forecast":"-0.9%","previous":"-5.5%","actColor":"bad","impact":"medium"},{"date":"Jan 30, 2025","actual":"-5.5%","forecast":"0.0%","previous":"2.2%","actColor":"bad","impact":"medium"},{"date":"Dec 30, 2024","actual":"2.2%","forecast":"0.9%","previous":"2.0%","actColor":"good","impact":"medium"},{"date":"Nov 27, 2024","actual":"2.0%","forecast":"-2.1%","previous":"7.4%","actColor":"good","impact":"medium"},{"date":"Oct 30, 2024","actual":"7.4%","forecast":"1.9%","previous":"0.6%","actColor":"good","impact":"medium"},{"date":"Sep 26, 2024","actual":"0.6%","forecast":"0.9%","previous":"-5.5%","actColor":"bad","impact":"medium"},{"date":"Aug 29, 2024","actual":"-5.5%","forecast":"0.2%","previous":"4.8%","actColor":"bad","impact":"medium"},{"date":"Jul 31, 2024","actual":"4.8%","forecast":"1.4%","previous":"-2.1%","actColor":"good","impact":"high"}]}